LICENSE
MANIFEST.in
README.md
setup.py
coolsms/__init__.py
coolsms/sender.py
coolsms.egg-info/PKG-INFO
coolsms.egg-info/SOURCES.txt
coolsms.egg-info/dependency_links.txt
coolsms.egg-info/requires.txt
coolsms.egg-info/top_level.txt