Metadata-Version: 1.0
Name: coolsms
Version: 0.2
Summary: Simple python library for korean SMS service provider CoolSMS(coolsms.co.kr)
Home-page: UNKNOWN
Author: lexifdev
Author-email: lexifdev@lxf.kr
License: BSD
Platform: any
